uoft_core/__init__.py
uoft_core/__main__.py
uoft_core/aruba.py
uoft_core/nested_data.py
uoft_core/other.py
uoft_core/_vendor/__init__.py
uoft_core/_vendor/decorator.py
uoft_core/_vendor/bluecat_libraries/__init__.py
uoft_core/_vendor/bluecat_libraries/address_manager/__init__.py
uoft_core/_vendor/bluecat_libraries/address_manager/_graphql/__init__.py
uoft_core/_vendor/bluecat_libraries/address_manager/_graphql/client.py
uoft_core/_vendor/bluecat_libraries/address_manager/_graphql/exceptions.py
uoft_core/_vendor/bluecat_libraries/address_manager/api/__init__.py
uoft_core/_vendor/bluecat_libraries/address_manager/api/_version.py
uoft_core/_vendor/bluecat_libraries/address_manager/api/client.py
uoft_core/_vendor/bluecat_libraries/address_manager/api/models.py
uoft_core/_vendor/bluecat_libraries/address_manager/api/serialization.py
uoft_core/_vendor/bluecat_libraries/address_manager/api/rest/__init__.py
uoft_core/_vendor/bluecat_libraries/address_manager/api/rest/auto/__init__.py
uoft_core/_vendor/bluecat_libraries/address_manager/api/rest/auto/_wadl_parser.py
uoft_core/_vendor/bluecat_libraries/address_manager/api/rest/auto/client.py
uoft_core/_vendor/bluecat_libraries/address_manager/api/rest/provisional/__init__.py
uoft_core/_vendor/bluecat_libraries/address_manager/api/rest/provisional/client.py
uoft_core/_vendor/bluecat_libraries/address_manager/api/rest/provisional/rest_dict.py
uoft_core/_vendor/bluecat_libraries/address_manager/api/rest/provisional/rest_entity_array.py
uoft_core/_vendor/bluecat_libraries/address_manager/api/rest/provisional/rest_fault.py
uoft_core/_vendor/bluecat_libraries/address_manager/constants/__init__.py
uoft_core/_vendor/bluecat_libraries/address_manager/constants/_enum.py
uoft_core/_vendor/bluecat_libraries/address_manager/constants/_version.py
uoft_core/_vendor/bluecat_libraries/address_manager/constants/access_right_values.py
uoft_core/_vendor/bluecat_libraries/address_manager/constants/additional_ip_service_type.py
uoft_core-1.0.1.dist-info/METADATA
uoft_core-1.0.1.dist-info/WHEEL
uoft_core-1.0.1.dist-info/RECORD
