Metadata-Version: 2.1
Name: uoft_core
Version: 1.0.1
Summary: an opinionated set of utilities designed to be easily included in any number of projects
Author-email: Alex Tremblay <alex.tremblay@utoronto.ca>, University of Toronto Governing Council <governing.council@utoronto.ca>
Requires-Python: >=3.10
Requires-Dist: loguru
Requires-Dist: requests>=2.20.0
Requires-Dist: rich
Requires-Dist: typer>=0.4.0
Provides-Extra: all
Requires-Dist: jinja2>=3.0; extra == 'all'
Requires-Dist: prompt-toolkit>=3.0.0; extra == 'all'
Requires-Dist: pydantic>=1.9; extra == 'all'
Requires-Dist: pytest>=6.0; extra == 'all'
Requires-Dist: semver; extra == 'all'
Requires-Dist: sentry-sdk>=1.4; extra == 'all'
